pd_money/__init__.py
pd_money/accessor.py
pd_money/allocate.py
pd_money/clean.py
pd_money/convert.py
pd_money/dates.py
pd_money/format.py
pd_money/growth.py
pd_money/performance.py
pd_money/summary.py
pd_money/valuation.py
pd_money/xirr.py
pd_money-0.1.2.dist-info/licenses/LICENSE
pd_money-0.1.2.dist-info/METADATA
pd_money-0.1.2.dist-info/WHEEL
pd_money-0.1.2.dist-info/top_level.txt
pd_money-0.1.2.dist-info/RECORD
