Metadata-Version: 2.4
Name: pd-money
Version: 0.1.2
Summary: A comprehensive pandas extension for financial data cleaning, performance analysis, and valuation.
Author-email: Ammar Alhajmee <ammar@alhajmee.com>
License: MIT License
Project-URL: Homepage, https://github.com/aalhajmee/pd-money
Project-URL: Repository, https://github.com/aalhajmee/pd-money
Project-URL: Issues, https://github.com/aalhajmee/pd-money/issues
Keywords: pandas,finance,money,cleaning,fintech,analysis
Classifier: Development Status :: 3 - Alpha
Classifier: Intended Audience :: Developers
Classifier: Intended Audience :: Financial and Insurance Industry
Classifier: License :: OSI Approved :: MIT License
Classifier: Programming Language :: Python :: 3
Classifier: Programming Language :: Python :: 3.9
Classifier: Programming Language :: Python :: 3.10
Classifier: Programming Language :: Python :: 3.11
Classifier: Programming Language :: Python :: 3.12
Requires-Python: >=3.9
License-File: LICENSE
Requires-Dist: pandas>=1.0.0
Requires-Dist: numpy>=1.20.0
Dynamic: license-file
